spikeinterface_poetry/__init__.py
spikeinterface_poetry-4.1.0.dist-info/LICENSE.md
spikeinterface_poetry-4.1.0.dist-info/METADATA
spikeinterface_poetry-4.1.0.dist-info/WHEEL
spikeinterface_poetry-4.1.0.dist-info/RECORD
