Metadata-Version: 2.1
Name: spikeinterface-poetry
Version: 4.1.0
Summary: Poetry packaging with extras for working with spikeinterface
Home-page: https://github.com/caniko/spikeinterface_poetry
License: BSD-4
Author: Can H. Tartanoglu
Author-email: canhtart@gmail.com
Requires-Python: >=3.8,<3.11
Classifier: License :: OSI Approved :: MIT License
Classifier: License :: Other/Proprietary License
Classifier: Operating System :: OS Independent
Classifier: Programming Language :: Python :: 3
Classifier: Programming Language :: Python :: 3.8
Classifier: Programming Language :: Python :: 3.9
Classifier: Programming Language :: Python :: 3.10
Classifier: Programming Language :: Python :: 3
Provides-Extra: all-sorters
Provides-Extra: docker
Provides-Extra: gui
Provides-Extra: herdingspikes
Provides-Extra: jupyter
Provides-Extra: klusta
Provides-Extra: mountainsort
Provides-Extra: phy
Provides-Extra: pykilosort
Provides-Extra: singularity
Provides-Extra: spyking-circus
Provides-Extra: spython
Provides-Extra: tridesclous
Requires-Dist: Cython ; extra == "klusta" or extra == "all-sorters"
Requires-Dist: PyQt5 ; extra == "gui" or extra == "tridesclous" or extra == "spyking-circus" or extra == "all-sorters"
Requires-Dist: docker ; extra == "docker"
Requires-Dist: herdingspikes (>=0.3.99,<0.4.0) ; extra == "herdingspikes" or extra == "all-sorters"
Requires-Dist: jupyter ; extra == "jupyter"
Requires-Dist: klusta (>=3.0.16,<4.0.0) ; extra == "klusta" or extra == "all-sorters"
Requires-Dist: klustakwik2 (>=0.2.7,<0.3.0) ; extra == "klusta" or extra == "all-sorters"
Requires-Dist: loky (>=3.0.0,<4.0.0) ; extra == "tridesclous" or extra == "all-sorters"
Requires-Dist: mountainsort4 (>=1.0.0,<2.0.0) ; extra == "mountainsort" or extra == "all-sorters"
Requires-Dist: numba
Requires-Dist: phy-poetry ; extra == "phy"
Requires-Dist: pyopencl (>=2022.1,<2023.0) ; extra == "tridesclous"
Requires-Dist: spikeinterface-gui ; extra == "gui"
Requires-Dist: spikeinterface[full,widgets]
Requires-Dist: spyking-circus (>=1.1.0,<2.0.0) ; extra == "spyking-circus" or extra == "all-sorters"
Requires-Dist: spython ; extra == "spython" or extra == "singularity"
Requires-Dist: tridesclous (>=1.6.5,<2.0.0) ; extra == "tridesclous" or extra == "all-sorters"
